souptools/__init__.py
souptools/__meta__.py
souptools/css_match.py
souptools/css_parser.py
souptools/css_types.py
souptools/pretty.py
souptools/util.py
souptools-2.1.7.dist-info/LICENSE.md
souptools-2.1.7.dist-info/METADATA
souptools-2.1.7.dist-info/WHEEL
souptools-2.1.7.dist-info/top_level.txt
souptools-2.1.7.dist-info/RECORD
