Metadata-Version: 2.1
Name: souptools
Version: 2.1.7
Summary: CSS tools
Author-email: Antony Wilson <antony.wilson@gmail.com>
Project-URL: Homepage, https://github.com/pypa/sampleproject
Classifier: Programming Language :: Python :: 3
Classifier: License :: OSI Approved :: MIT License
Classifier: Operating System :: OS Independent
Requires-Python: >=3.5
License-File: LICENSE.md
